main.py
passwordstore-1.0.0.dist-info/LICENSE
passwordstore-1.0.0.dist-info/METADATA
passwordstore-1.0.0.dist-info/WHEEL
passwordstore-1.0.0.dist-info/entry_points.txt
passwordstore-1.0.0.dist-info/top_level.txt
passwordstore-1.0.0.dist-info/RECORD
