Metadata-Version: 2.1
Name: passwordstore
Version: 1.0.0
Summary: Small utility to generate secure passwords from masterpass word
Home-page: https://github.com/maksloboda/PasswordStore
Author: MaksL
Author-email: contactmaksloboda@gmail.com
License: UNKNOWN
Project-URL: Bug Tracker, https://github.com/maksloboda/PasswordStore/issues
Platform: UNKNOWN
Classifier: Programming Language :: Python :: 3
Classifier: License :: OSI Approved :: MIT License
Classifier: Operating System :: OS Independent
Requires-Python: >=3.6
License-File: LICENSE
Requires-Dist: click
Requires-Dist: cryptography
Requires-Dist: pyperclip
